README.txt
setup.py
Products/__init__.py
Products.MaildropHost.egg-info/PKG-INFO
Products.MaildropHost.egg-info/SOURCES.txt
Products.MaildropHost.egg-info/dependency_links.txt
Products.MaildropHost.egg-info/entry_points.txt
Products.MaildropHost.egg-info/namespace_packages.txt
Products.MaildropHost.egg-info/not-zip-safe
Products.MaildropHost.egg-info/requires.txt
Products.MaildropHost.egg-info/top_level.txt
Products/MaildropHost/CHANGES.txt
Products/MaildropHost/COPYRIGHT.txt
Products/MaildropHost/DEPENDENCIES.txt
Products/MaildropHost/HISTORY.txt
Products/MaildropHost/INSTALL.txt
Products/MaildropHost/LICENSE.txt
Products/MaildropHost/MaildropHost.py
Products/MaildropHost/README.txt
Products/MaildropHost/SAMPLE_MAIL.txt
Products/MaildropHost/TransactionalMixin.py
Products/MaildropHost/VERSION.txt
Products/MaildropHost/__init__.py
Products/MaildropHost/config
Products/MaildropHost/dtml/add.dtml
Products/MaildropHost/dtml/edit.dtml
Products/MaildropHost/dtml/log.dtml
Products/MaildropHost/help/MaildropHost.stx
Products/MaildropHost/help/add.stx
Products/MaildropHost/help/edit.stx
Products/MaildropHost/help/log.stx
Products/MaildropHost/maildrop/__init__.py
Products/MaildropHost/maildrop/maildrop.py
Products/MaildropHost/maildrop/stringparse.py
Products/MaildropHost/maildrop/bin/README
Products/MaildropHost/maildrop/bin/maildrop-redhat
Products/MaildropHost/maildrop/bin/maildrop-suse
Products/MaildropHost/maildrop/bin/maildropctl
Products/MaildropHost/maildrop/bin/start_maildrop
Products/MaildropHost/maildrop/bin/start_maildrop.bat
Products/MaildropHost/maildrop/bin/stop_maildrop
Products/MaildropHost/maildrop/testing/README.txt
Products/MaildropHost/maildrop/testing/config.py
Products/MaildropHost/maildrop/testing/make_emails.py
Products/MaildropHost/maildrop/testing/start_maildrop
Products/MaildropHost/maildrop/testing/stop_maildrop
Products/MaildropHost/seleniumtests/test1_instantiation.html
Products/MaildropHost/seleniumtests/test3_deletion.html
Products/MaildropHost/tests/__init__.py
Products/MaildropHost/tests/badconfig
Products/MaildropHost/tests/dummyconfig
Products/MaildropHost/tests/test_Email.py
Products/MaildropHost/tests/test_MaildropHost.py
Products/MaildropHost/www/maildrop.gif