Metadata-Version: 1.0
Name: Products.MaildropHost
Version: 2.1
Summary: Asynchronous transaction-aware MailHost replacement for Zope 2
Home-page: http://pypi.python.org/pypi/Products.MaildropHost
Author: Jens Vagelpohl
Author-email: jens@dataflake.org
License: ZPL 2.1 (http://www.zope.org/Resources/License/ZPL-2.1)
Keywords: web zope zope2 mail smtp
Platform: UNKNOWN
Classifier: Development Status :: 5 - Production/Stable
Classifier: Framework :: Zope2
Classifier: Intended Audience :: Developers
Classifier: License :: OSI Approved :: Zope Public License
Classifier: Operating System :: POSIX
Classifier: Programming Language :: Python
Classifier: Topic :: Communications :: Email
Classifier: Topic :: Software Development
